pyroot/__init__.py
pyroot/_pyroot_new.py
pyroot/_pyroot_old.py
PyRoot-0.3.0.dist-info/LICENSE
PyRoot-0.3.0.dist-info/METADATA
PyRoot-0.3.0.dist-info/WHEEL
PyRoot-0.3.0.dist-info/top_level.txt
PyRoot-0.3.0.dist-info/RECORD
