Metadata-Version: 2.1
Name: PyRoot
Version: 0.3.0
Summary: The purpose of this Python library is to provide implementations of advanced bracketed root-finding methods for single-variable functions.
Home-page: https://github.com/SimpleArt/pyroot
Author: Jack Nguyen
Author-email: jackyeenguyen@gmail.com
Classifier: Programming Language :: Python :: 3.8
Classifier: License :: OSI Approved :: MIT License
Classifier: Operating System :: OS Independent
Requires-Python: >=3.8
License-File: LICENSE
